{
  "objectID": 20003,
  "irn": 20003,
  "ecatalogue_key": 11003,
  "TitAccessionNo": "2001.35.11029",
  "CreDateCreated": "c. 1968",
  "CreEarliestDate": "1965",
  "CreLatestDate": "1971",
  "PhyMediumComments": "black-and-white: Kodak safety film",
  "CatDescriptText": " Harper was a promoter of jazz music and owned a jazz club, which attracted a multi-racial audience.  Father Michael was also a promoter of jazz artists.  In the background are three figurative drawings hung on a wood panel wall.",
  "TitMainTitle": "Walt Harper, Father Michael Williams, and George Wein, in interior with wood paneling",
  "CatSubject_tab": "Harper, Walter, 1932-Priests--Pennsylvania--Pittsburgh.Wein, George.Interiors--Pennsylvania--Pittsburgh.",
  "AdmGUIDValue_tab": "7f6c9f9e-3247-492d-8184-0d04bcf43d15",
  "AdmPublishWebNoPassword": "Yes",
  "image_url": "https://cmoa-collection-images.s3.amazonaws.com/teenie/26857/sizes/20003-1680.jpg",
  "datetime": "1965-01-01 00:00:00",
  "people": [
    "Michael",
    "Walt Harper",
    "Harper",
    "George Wein",
    "Michael Williams"
  ],
  "places": [
    {
      "type": "locality",
      "score": 50,
      "long_name": "Pittsburgh",
      "short_name": "Pittsburgh"
    },
    {
      "type": "administrative_area_level_2",
      "score": 30,
      "long_name": "Allegheny County",
      "short_name": "Allegheny County"
    },
    {
      "type": "administrative_area_level_1",
      "score": 20,
      "long_name": "Pennsylvania",
      "short_name": "PA"
    },
    {
      "type": "country",
      "score": 10,
      "long_name": "United States",
      "short_name": "US"
    }
  ],
  "people_count": 6,
  "google_text_in_image": "",
  "subjects": [
    "Interior architecture",
    "Interiors",
    "Michael"
  ],
  "keywords": [
    {
      "keyword": "man",
      "score": 0.499580641500651
    },
    {
      "keyword": "suit",
      "score": 0.343992514711507
    },
    {
      "keyword": "Michael",
      "score": 0.3333333333333333
    },
    {
      "keyword": "Walt Harper",
      "score": 0.3333333333333333
    },
    {
      "keyword": "Michael Williams",
      "score": 0.3333333333333333
    },
    {
      "keyword": "Harper",
      "score": 0.3333333333333333
    },
    {
      "keyword": "Harper, Walter, 1932-Priests",
      "score": 0.3333333333333333
    },
    {
      "keyword": "George Wein",
      "score": 0.3333333333333333
    },
    {
      "keyword": "Interiors",
      "score": 0.3333333333333333
    },
    {
      "keyword": "Wein, George",
      "score": 0.3333333333333333
    },
    {
      "keyword": "black and white",
      "score": 0.2958345333333333
    },
    {
      "keyword": "photography",
      "score": 0.2739069333333333
    },
    {
      "keyword": "snapshot",
      "score": 0.27255816666666666
    },
    {
      "keyword": "gentleman",
      "score": 0.2610535333333333
    },
    {
      "keyword": "monochrome photography",
      "score": 0.2482057666666667
    },
    {
      "keyword": "conversation",
      "score": 0.21925113333333335
    },
    {
      "keyword": "monochrome",
      "score": 0.21165103333333335
    },
    {
      "keyword": "communication",
      "score": 0.2035250815770467
    }
  ],
  "image_url_small": "https://cmoa-collection-images.s3.amazonaws.com/teenie/26857/sizes/20003-840.jpg",
  "image_url_thumb": "https://cmoa-collection-images.s3.amazonaws.com/teenie/26857/sizes/20003-210.jpg",
  "date_timestamp_earliest": -157766400.0,
  "date_timestamp_latest": 31536000.0,
  "decades": []
}