{
  "objectID": 38859,
  "irn": 38859,
  "ecatalogue_key": 26286,
  "TitAccessionNo": "2001.35.26318",
  "CreDateCreated": "c. 1940-1950",
  "CreEarliestDate": "1940",
  "CreLatestDate": "1950",
  "PhyMediumComments": "black-and-white: Agfa safety film",
  "CatDescriptText": "",
  "TitMainTitle": "Portrait of woman, possibly Mozella Wilkerson, wearing dark dress with squared neckline with gathers on corners, and floral applique on sleeves, posed in front of moire background, in Harris Studio",
  "CatSubject_tab": "Women--Pennsylvania--Pittsburgh.Portraits--Pennsylvania--Pittsburgh.Studio portraits--Pennsylvania--Pittsburgh.Harris Studio (Pittsburgh, Pa.)Women--Portraits--Pennsylvania--Pittsburgh.",
  "AdmGUIDValue_tab": "91dc4f94-f1df-457f-a4fa-ccb3ae910bcd",
  "AdmPublishWebNoPassword": "Yes",
  "image_url": "https://cmoa-collection-images.s3.amazonaws.com/teenie/45001/sizes/38859-1680.jpg",
  "datetime": "1940-01-01 00:00:00",
  "people": [
    "Mozella Wilkerson",
    "Harris Studio"
  ],
  "places": [
    {
      "type": "locality",
      "score": 50,
      "long_name": "Pittsburgh",
      "short_name": "Pittsburgh"
    },
    {
      "type": "administrative_area_level_2",
      "score": 30,
      "long_name": "Allegheny County",
      "short_name": "Allegheny County"
    },
    {
      "type": "administrative_area_level_1",
      "score": 20,
      "long_name": "Pennsylvania",
      "short_name": "PA"
    },
    {
      "type": "country",
      "score": 10,
      "long_name": "United States",
      "short_name": "US"
    }
  ],
  "people_count": 1,
  "google_text_in_image": "",
  "subjects": [
    "Portraits",
    "Women"
  ],
  "keywords": [
    {
      "keyword": "person",
      "score": 0.4768978803629557
    },
    {
      "keyword": "portrait",
      "score": 0.40701749956054695
    },
    {
      "keyword": "lady",
      "score": 0.374301071636963
    },
    {
      "keyword": "smile",
      "score": 0.3605219449198403
    },
    {
      "keyword": "Women",
      "score": 0.3333333333333333
    },
    {
      "keyword": "Studio portraits",
      "score": 0.3333333333333333
    },
    {
      "keyword": "Harris Studio ",
      "score": 0.3333333333333333
    },
    {
      "keyword": ")Women",
      "score": 0.3333333333333333
    },
    {
      "keyword": "Portraits",
      "score": 0.3333333333333333
    },
    {
      "keyword": "facial expression",
      "score": 0.3112684333333333
    },
    {
      "keyword": "model",
      "score": 0.30826643902181
    },
    {
      "keyword": "beauty",
      "score": 0.3046029333333333
    },
    {
      "keyword": "girl",
      "score": 0.30096022333333333
    },
    {
      "keyword": "black and white",
      "score": 0.29756325333333333
    },
    {
      "keyword": "photography",
      "score": 0.28933525
    },
    {
      "keyword": "human",
      "score": 0.28101023056640634
    },
    {
      "keyword": "photo shoot",
      "score": 0.27808479999999997
    },
    {
      "keyword": "snapshot",
      "score": 0.27255816666666666
    },
    {
      "keyword": "emotion",
      "score": 0.27001341333333334
    },
    {
      "keyword": "monochrome photography",
      "score": 0.26888090000000003
    },
    {
      "keyword": "eye",
      "score": 0.26732553333333336
    },
    {
      "keyword": "sitting",
      "score": 0.24164939
    },
    {
      "keyword": "happiness",
      "score": 0.24059028400187168
    },
    {
      "keyword": "black hair",
      "score": 0.23277191333333333
    },
    {
      "keyword": "princess",
      "score": 0.22055892944335934
    },
    {
      "keyword": "organ",
      "score": 0.22020023333333336
    },
    {
      "keyword": "portrait photography",
      "score": 0.21937333333333334
    },
    {
      "keyword": "monochrome",
      "score": 0.21505686666666668
    }
  ],
  "image_url_small": "https://cmoa-collection-images.s3.amazonaws.com/teenie/45001/sizes/38859-840.jpg",
  "image_url_thumb": "https://cmoa-collection-images.s3.amazonaws.com/teenie/45001/sizes/38859-210.jpg",
  "date_timestamp_earliest": -946771200.0,
  "date_timestamp_latest": -631152000.0,
  "decades": []
}