{
  "objectID": 61276,
  "irn": 61276,
  "ecatalogue_key": 47225,
  "TitAccessionNo": "2001.35.47268",
  "CreDateCreated": "May-June 1957",
  "CreEarliestDate": "1957-05-01",
  "CreLatestDate": "1957-06-30",
  "PhyMediumComments": "black-and-white: Kodak safety film",
  "CatDescriptText": "Cutline of image published in Pittsburgh Courier newspaper, June 8, 1957, pg. A13 reads: \"Magic Surrounds Girl Friends' Pittsburgh Meet - Next Year's Hostesses - The Roanoke (Va.) chapter will entertain the GF's in magnificent Gerenbrier [sic] Hotel in White Sulphur Springs, W. Va. Seated : Natalie Clayton, Helene Downing, Polly Weeden and Natalie Holmes.  Standing: Evelyn Skipper, Anne Coleman, La Verne Full...Gladys Fulton, Adelaide Johnson, Julia Law, Anne Patterson, Alyce Moore and Doris Elam\"",
  "TitMainTitle": "Group portrait of members of Roanoke chapter of Girl Friends, Inc., seated: Natalie Clayton, Helene Downing, Polly Weeden, Natalie Holmes; standing: Evelyn Skipper, Anne Coleman, La Verne Full, Gladys Fulton, Adelaide Johnson, Julia Law, Anne Patterson, Alyce Moore, and Doris Elam, posed in Webster Hall",
  "CatSubject_tab": "Group portraits--Pennsylvania--Pittsburgh.Mural painting and decoration--Pennsylvania--Pittsburgh.Women--Pennsylvania--Pittsburgh.Interiors--Pennsylvania--Pittsburgh.Webster Hall (Pittsburgh, Pa.)",
  "AdmGUIDValue_tab": "a72d37f8-10fe-443e-a4da-bc7d7359c760",
  "AdmPublishWebNoPassword": "Yes",
  "image_url": "https://cmoa-collection-images.s3.amazonaws.com/teenie/69488/sizes/61276-1680.jpg",
  "datetime": "1957-05-01 00:00:00",
  "people": [
    "Polly Weeden",
    "Doris Elam",
    "Alyce Moore",
    "Julia Law",
    "Evelyn Skipper",
    "Natalie Clayton",
    "Anne Patterson",
    "Gladys Fulton",
    "Helene Downing",
    "Natalie Holmes",
    "Anne Coleman"
  ],
  "places": [
    {
      "type": "neighborhood",
      "score": 80,
      "long_name": "North Oakland",
      "short_name": "North Oakland"
    },
    {
      "type": "locality",
      "score": 50,
      "long_name": "Pittsburgh",
      "short_name": "Pittsburgh"
    },
    {
      "type": "route",
      "score": 50,
      "long_name": "North Dithridge Street",
      "short_name": "N Dithridge St"
    },
    {
      "type": "route",
      "score": 50,
      "long_name": "Delafield Road",
      "short_name": "Delafield Rd"
    },
    {
      "type": "route",
      "score": 50,
      "long_name": "Towne Square Way",
      "short_name": "Towne Square Way"
    },
    {
      "type": "locality",
      "score": 50,
      "long_name": "Morgantown",
      "short_name": "Morgantown"
    },
    {
      "type": "administrative_area_level_3",
      "score": 40,
      "long_name": "O'Hara Township",
      "short_name": "O'Hara Township"
    },
    {
      "type": "administrative_area_level_2",
      "score": 30,
      "long_name": "Allegheny County",
      "short_name": "Allegheny County"
    },
    {
      "type": "administrative_area_level_2",
      "score": 30,
      "long_name": "Monongalia County",
      "short_name": "Monongalia County"
    },
    {
      "type": "administrative_area_level_1",
      "score": 20,
      "long_name": "Pennsylvania",
      "short_name": "PA"
    },
    {
      "type": "administrative_area_level_1",
      "score": 20,
      "long_name": "West Virginia",
      "short_name": "WV"
    },
    {
      "type": "country",
      "score": 10,
      "long_name": "United States",
      "short_name": "US"
    }
  ],
  "people_count": 13,
  "google_text_in_image": "",
  "subjects": [
    "Maya mural painting and decoration",
    "Women",
    "Interior architecture",
    "Mural painting and decoration, Mogul Empire",
    "Face--Muscles--Abnormalities--Treatment",
    "Area 13--Scienze economiche e statistiche",
    "H\u00f4tel de ville (Tours, France)",
    "Osteopathic students",
    "Herbicides--Physiological effect",
    "Costa Rica--History--1986-",
    "Trachyphloeus",
    "Portraits, Group",
    "Horror in art",
    "Girl Friends, Inc.",
    "Interiors",
    "Private flying--Accidents--United States--Periodicals",
    "Zimbabwe--Economic policy",
    "School sports--Fiction",
    "Reinstatement",
    "Skin--Cancer--Risk factors--Congresses",
    "Pittsburgh courier"
  ],
  "keywords": [
    {
      "keyword": "people",
      "score": 0.415109386850993
    },
    {
      "keyword": "dress",
      "score": 0.374976135024007
    },
    {
      "keyword": "Webster Hall",
      "score": 0.3333333333333333
    },
    {
      "keyword": "Women",
      "score": 0.3333333333333333
    },
    {
      "keyword": "Group portraits",
      "score": 0.3333333333333333
    },
    {
      "keyword": "Roanoke",
      "score": 0.3333333333333333
    },
    {
      "keyword": "La Verne Full",
      "score": 0.3333333333333333
    },
    {
      "keyword": "A13",
      "score": 0.3333333333333333
    },
    {
      "keyword": "Magic Surrounds Girl Friends' Pittsburgh Meet - Next Year's Hostesses - The Roanoke",
      "score": 0.3333333333333333
    },
    {
      "keyword": "Girl Friends, Inc.",
      "score": 0.3333333333333333
    },
    {
      "keyword": "Julia Law",
      "score": 0.3333333333333333
    },
    {
      "keyword": "Anne Patterson",
      "score": 0.3333333333333333
    },
    {
      "keyword": "June 8, 1957",
      "score": 0.3333333333333333
    },
    {
      "keyword": "Mural painting and decoration",
      "score": 0.3333333333333333
    },
    {
      "keyword": "Pittsburgh Courier",
      "score": 0.3333333333333333
    },
    {
      "keyword": "Mural painting and decoration, ...",
      "score": 0.3333333333333333
    },
    {
      "keyword": "Webster Hall ",
      "score": 0.3333333333333333
    },
    {
      "keyword": "Anne Coleman",
      "score": 0.3333333333333333
    },
    {
      "keyword": "Interiors",
      "score": 0.3333333333333333
    },
    {
      "keyword": "social group",
      "score": 0.32045443333333334
    },
    {
      "keyword": "facial expression",
      "score": 0.31206365333333336
    },
    {
      "keyword": "family",
      "score": 0.3069788815958659
    },
    {
      "keyword": "black and white",
      "score": 0.30626934666666666
    },
    {
      "keyword": "standing",
      "score": 0.2968032
    },
    {
      "keyword": "child",
      "score": 0.29067133881449364
    },
    {
      "keyword": "fun",
      "score": 0.2841928026346842
    },
    {
      "keyword": "monochrome photography",
      "score": 0.2835333
    },
    {
      "keyword": "vintage clothing",
      "score": 0.2833140333333333
    },
    {
      "keyword": "photography",
      "score": 0.27395073333333336
    },
    {
      "keyword": "snapshot",
      "score": 0.27255816666666666
    },
    {
      "keyword": "girl",
      "score": 0.26718353333333333
    },
    {
      "keyword": "monochrome",
      "score": 0.24288678333333333
    },
    {
      "keyword": "smile",
      "score": 0.23855964333333335
    },
    {
      "keyword": "happiness",
      "score": 0.236665604058838
    },
    {
      "keyword": "ceremony",
      "score": 0.22715469571380617
    },
    {
      "keyword": "wedding",
      "score": 0.20897742665201835
    },
    {
      "keyword": "friendship",
      "score": 0.20588345949747722
    }
  ],
  "image_url_small": "https://cmoa-collection-images.s3.amazonaws.com/teenie/69488/sizes/61276-840.jpg",
  "image_url_thumb": "https://cmoa-collection-images.s3.amazonaws.com/teenie/69488/sizes/61276-210.jpg",
  "date_timestamp_earliest": -399859200.0,
  "date_timestamp_latest": -394675200.0,
  "decades": [
    "1950s"
  ]
}