{
  "objectID": 65790,
  "irn": 65790,
  "ecatalogue_key": 51566,
  "TitAccessionNo": "2001.35.51609",
  "CreDateCreated": "c. 1950",
  "CreEarliestDate": "1945",
  "CreLatestDate": "1955",
  "PhyMediumComments": "black-and-white: Kodak safety film",
  "CatDescriptText": "",
  "TitMainTitle": "Funeral with crowd of women and men, some in military uniforms, including three front left in honor guard holding rifles facing back, gathered around burial plot with casket draped in an American flag, in cemetery with trees",
  "CatSubject_tab": "Crowds--Pennsylvania--Pittsburgh.Men--Pennsylvania--Pittsburgh.Women--Pennsylvania--Pittsburgh.Firearms--Pennsylvania--Pittsburgh.Military uniforms--Pennsylvania--Pittsburgh.Funeral rites and ceremonies--Pennsylvania--Pittsburgh.Caskets--Pennsylvania--Pittsburgh.Flags--Pennsylvania--Pittsburgh.Trees--Pennsylvania--Pittsburgh.",
  "AdmGUIDValue_tab": "489e99ed-d4a9-4346-9619-8ed76cc64ab7",
  "AdmPublishWebNoPassword": "Yes",
  "image_url": "https://cmoa-collection-images.s3.amazonaws.com/teenie/75498/sizes/65790-1680.jpg",
  "datetime": "1945-01-01 00:00:00",
  "people": [],
  "places": [
    {
      "type": "locality",
      "score": 50,
      "long_name": "Pittsburgh",
      "short_name": "Pittsburgh"
    },
    {
      "type": "administrative_area_level_2",
      "score": 30,
      "long_name": "Allegheny County",
      "short_name": "Allegheny County"
    },
    {
      "type": "administrative_area_level_1",
      "score": 20,
      "long_name": "Pennsylvania",
      "short_name": "PA"
    },
    {
      "type": "country",
      "score": 10,
      "long_name": "United States",
      "short_name": "US"
    }
  ],
  "people_count": 18,
  "google_text_in_image": "",
  "subjects": [
    "Flags",
    "Trees",
    "Zen funeral rites and ceremonies",
    "Men",
    "Women",
    "Firearms",
    "American",
    "Military uniforms",
    "Chests",
    "Boxes",
    "Funeral rites and ceremonies",
    "Crowds"
  ],
  "keywords": [
    {
      "keyword": "tree",
      "score": 0.37236322126871735
    },
    {
      "keyword": "Flags",
      "score": 0.3333333333333333
    },
    {
      "keyword": "Trees",
      "score": 0.3333333333333333
    },
    {
      "keyword": "Men",
      "score": 0.3333333333333333
    },
    {
      "keyword": "Funeral rites and ceremonies, Zen",
      "score": 0.3333333333333333
    },
    {
      "keyword": "Women",
      "score": 0.3333333333333333
    },
    {
      "keyword": "Firearms",
      "score": 0.3333333333333333
    },
    {
      "keyword": "American",
      "score": 0.3333333333333333
    },
    {
      "keyword": "Military uniforms",
      "score": 0.3333333333333333
    },
    {
      "keyword": "Caskets",
      "score": 0.3333333333333333
    },
    {
      "keyword": "Funeral rites and ceremonies",
      "score": 0.3333333333333333
    },
    {
      "keyword": "Crowds",
      "score": 0.3333333333333333
    },
    {
      "keyword": "black and white",
      "score": 0.30953766666666666
    },
    {
      "keyword": "monochrome photography",
      "score": 0.2863514
    },
    {
      "keyword": "infrastructure",
      "score": 0.2852636
    },
    {
      "keyword": "standing",
      "score": 0.27616471000000004
    },
    {
      "keyword": "photography",
      "score": 0.27209504333333334
    },
    {
      "keyword": "monochrome",
      "score": 0.2503218
    },
    {
      "keyword": "street",
      "score": 0.24424546666666666
    },
    {
      "keyword": "recreation",
      "score": 0.22324972758280434
    }
  ],
  "image_url_small": "https://cmoa-collection-images.s3.amazonaws.com/teenie/75498/sizes/65790-840.jpg",
  "image_url_thumb": "https://cmoa-collection-images.s3.amazonaws.com/teenie/75498/sizes/65790-210.jpg",
  "date_timestamp_earliest": -788918400.0,
  "date_timestamp_latest": -473385600.0,
  "decades": []
}