{
  "objectID": 7077,
  "irn": 7077,
  "ecatalogue_key": 4372,
  "TitAccessionNo": "2001.35.4381",
  "CreDateCreated": "1962",
  "CreEarliestDate": "1962",
  "CreLatestDate": "1962",
  "PhyMediumComments": "black-and-white: Kodak safety film",
  "CatDescriptText": "",
  "TitMainTitle": "View of crowd with placards reading \"Pennsylvania The Forgotten State\" and \"Jobs Not Jibes\" and \"Build a Better Pennsylvania, Scranton for Governor, outside Scranton - Van Zandt campaign headquarters",
  "CatSubject_tab": "Men--Pennsylvania--Pittsburgh.Women--Pennsylvania--Pittsburgh.Crowds--Pennsylvania--Pittsburgh.Political campaigns--Pennsylvania--Pittsburgh.Signs--Pennsylvania--Pittsburgh.Flags--Pennsylvania--Pittsburgh.Children--Pennsylvania--Pittsburgh.Police officers--Pennsylvania--Pittsburgh.Buildings--Pennsylvania--Pittsburgh.Telephone poles--Pennsylvania--Pittsburgh.",
  "AdmGUIDValue_tab": "4299575d-9443-4112-9108-a271b390370d",
  "AdmPublishWebNoPassword": "Yes",
  "image_url": "https://cmoa-collection-images.s3.amazonaws.com/teenie/19502/sizes/7077-1680.jpg",
  "datetime": "1962-01-01 00:00:00",
  "people": [],
  "places": [
    {
      "type": "route",
      "score": 50,
      "long_name": "Kappa Drive",
      "short_name": "Kappa Dr"
    },
    {
      "type": "locality",
      "score": 50,
      "long_name": "Pittsburgh",
      "short_name": "Pittsburgh"
    },
    {
      "type": "administrative_area_level_3",
      "score": 40,
      "long_name": "O'Hara Township",
      "short_name": "O'Hara Township"
    },
    {
      "type": "administrative_area_level_2",
      "score": 30,
      "long_name": "Allegheny County",
      "short_name": "Allegheny County"
    },
    {
      "type": "administrative_area_level_1",
      "score": 20,
      "long_name": "Pennsylvania",
      "short_name": "PA"
    },
    {
      "type": "country",
      "score": 10,
      "long_name": "United States",
      "short_name": "US"
    }
  ],
  "people_count": 31,
  "google_text_in_image": "COURT\n",
  "subjects": [
    "Crowds",
    "Buildings",
    "Children",
    "Women",
    "Flags",
    "Signs and signboards",
    "Men",
    "Political campaigns",
    "Signs and symbols",
    "Police"
  ],
  "keywords": [
    {
      "keyword": "people",
      "score": 0.35963342651123037
    },
    {
      "keyword": "Crowds",
      "score": 0.3333333333333333
    },
    {
      "keyword": "Buildings",
      "score": 0.3333333333333333
    },
    {
      "keyword": "Children",
      "score": 0.3333333333333333
    },
    {
      "keyword": "Telephone poles",
      "score": 0.3333333333333333
    },
    {
      "keyword": "Women",
      "score": 0.3333333333333333
    },
    {
      "keyword": "Pennsylvania The Forgotten State",
      "score": 0.3333333333333333
    },
    {
      "keyword": "Flags",
      "score": 0.3333333333333333
    },
    {
      "keyword": "Scranton - Van Zandt",
      "score": 0.3333333333333333
    },
    {
      "keyword": "Police officers",
      "score": 0.3333333333333333
    },
    {
      "keyword": "Men",
      "score": 0.3333333333333333
    },
    {
      "keyword": "Jobs Not Jibes",
      "score": 0.3333333333333333
    },
    {
      "keyword": "Political campaigns",
      "score": 0.3333333333333333
    },
    {
      "keyword": "Signs",
      "score": 0.3333333333333333
    },
    {
      "keyword": "Build a Better Pennsylvania",
      "score": 0.3333333333333333
    },
    {
      "keyword": "city",
      "score": 0.3310241025675457
    },
    {
      "keyword": "crowd",
      "score": 0.3288548
    },
    {
      "keyword": "black and white",
      "score": 0.30623206666666664
    },
    {
      "keyword": "monochrome photography",
      "score": 0.27646706666666665
    },
    {
      "keyword": "audience",
      "score": 0.26969154666666667
    },
    {
      "keyword": "monochrome",
      "score": 0.24098615
    },
    {
      "keyword": "religion",
      "score": 0.20422155891876217
    }
  ],
  "image_url_small": "https://cmoa-collection-images.s3.amazonaws.com/teenie/19502/sizes/7077-840.jpg",
  "image_url_thumb": "https://cmoa-collection-images.s3.amazonaws.com/teenie/19502/sizes/7077-210.jpg",
  "date_timestamp_earliest": -252460800.0,
  "date_timestamp_latest": -252460800.0,
  "decades": [
    "1960s"
  ]
}