{
	"ecatalogue_key": 9327,
	"irn": 17704,
	"TitAccessionNo": "2001.35.9353",
	"CreDateCreated": "c. 1950-1975",
	"CreEarliestDate": "1950",
	"CreLatestDate": "1975",
	"PhyMediumComments": "black-and-white: Kodak safety film",
	"CatDescriptText": "",
	"TitMainTitle": "Man posing with Egyptian style hand gestures and hat at his feet, in room with curtain and carpet with urn pattern",
	"CreCountry_tab": "United States",
	"CreState_tab": "",
	"CreDistrict_tab": "",
	"CreCity_tab": "",
	"CrePlaceQualifier_tab": "",
	"CatSubject_tab": "Men--Pennsylvania--Pittsburgh.Portraits--Pennsylvania--Pittsburgh.Men--Portraits--Pennsylvania--Pittsburgh.",
	"AdmGUIDValue_tab": "7698b6b0-d9cc-46f7-a819-0ffa9be9fd07",
	"AdmPublishWebNoPassword": "Yes",
	"MultiMedia_irn": 25381,
	"MulMultiMediaRef_key": 9335,
	"image_url": "https://cmoa-collection-images.s3.amazonaws.com/teenie/25381/sizes/17704-1680.jpg"
}