{
	"ecatalogue_key": 10986,
	"irn": 19966,
	"TitAccessionNo": "2001.35.11012",
	"CreDateCreated": "c. 1930-1950",
	"CreEarliestDate": "1930",
	"CreLatestDate": "1950",
	"PhyMediumComments": "black-and-white: Agfa safety film",
	"CatDescriptText": "",
	"TitMainTitle": "Woman wearing bikini with fringe and flower in her hair dancing, with band leader and all-girl band in background, with bass, saxophones and drums",
	"CreCountry_tab": "United States",
	"CreState_tab": "",
	"CreDistrict_tab": "",
	"CreCity_tab": "",
	"CrePlaceQualifier_tab": "",
	"CatSubject_tab": "Musical instruments--Pennsylvania--Pittsburgh.Musicians--Pennsylvania--Pittsburgh.Women--Pennsylvania--Pittsburgh.Men--Pennsylvania--Pittsburgh.Dancers--Pennsylvania--Pittsburgh.",
	"AdmGUIDValue_tab": "5d40b779-1047-42a1-8cd7-ffa0aa4d12ed",
	"AdmPublishWebNoPassword": "Yes",
	"MultiMedia_irn": 27057,
	"MulMultiMediaRef_key": 10994,
	"image_url": "https://cmoa-collection-images.s3.amazonaws.com/teenie/27057/sizes/19966-1680.jpg"
}