{
	"ecatalogue_key": 12878,
	"irn": 22245,
	"TitAccessionNo": "2001.35.12908",
	"CreDateCreated": "c. 1950-1970",
	"CreEarliestDate": "1950",
	"CreLatestDate": "1970",
	"PhyMediumComments": "black-and-white: Kodak safety film",
	"CatDescriptText": "",
	"TitMainTitle": "Basement with pipes, utility box, and window on left",
	"CreCountry_tab": "United States",
	"CreState_tab": "",
	"CreDistrict_tab": "",
	"CreCity_tab": "",
	"CrePlaceQualifier_tab": "",
	"CatSubject_tab": "Basements--Pennsylvania--Pittsburgh.",
	"AdmGUIDValue_tab": "c1a2cdde-8d67-4f96-a74c-de9dd4073253",
	"AdmPublishWebNoPassword": "Yes",
	"MultiMedia_irn": 29001,
	"MulMultiMediaRef_key": 12886,
	"image_url": "https://cmoa-collection-images.s3.amazonaws.com/teenie/29001/sizes/22245-1680.jpg"
}