{
	"ecatalogue_key": 1020,
	"irn": 2423,
	"TitAccessionNo": "2001.35.1022",
	"CreDateCreated": "c. 1935-1945",
	"CreEarliestDate": "1925",
	"CreLatestDate": "1950",
	"PhyMediumComments": "black-and-white: Agfa safety film",
	"CatDescriptText": "",
	"TitMainTitle": "Single male boxer, fists raised, in Harris Studio",
	"CreCountry_tab": "United States",
	"CreState_tab": "",
	"CreDistrict_tab": "",
	"CreCity_tab": "",
	"CrePlaceQualifier_tab": "",
	"CatSubject_tab": "Men--Pennsylvania--Pittsburgh.Boxers--Pennsylvania--Pittsburgh.Boxing--Pennsylvania--Pittsburgh.Portraits--Pennsylvania--Pittsburgh.Harris Studio (Pittsburgh, Pa.)Sports--Pennsylvania--Pittsburgh.Men--Portraits--Pennsylvania--Pittsburgh.",
	"AdmGUIDValue_tab": "1916756e-0ffa-4cf2-a56b-e84666a0f812",
	"AdmPublishWebNoPassword": "Yes",
	"MultiMedia_irn": 15507,
	"MulMultiMediaRef_key": 1022,
	"image_url": "https://cmoa-collection-images.s3.amazonaws.com/teenie/15507/sizes/2423-1680.jpg"
}