{
	"ecatalogue_key": 20445,
	"irn": 32373,
	"TitAccessionNo": "2001.35.20476",
	"CreDateCreated": "1963",
	"CreEarliestDate": "1963",
	"CreLatestDate": "1963",
	"PhyMediumComments": "black-and-white: Kodak safety film",
	"CatDescriptText": "",
	"TitMainTitle": "Group portrait of women, men, and children, including woman on left wearing striped sweater suit, and Robert Washington back row third from right with moustache, posed possibly in Calvary Church, another version",
	"CreCountry_tab": "United States",
	"CreState_tab": "",
	"CreDistrict_tab": "",
	"CreCity_tab": "",
	"CrePlaceQualifier_tab": "",
	"CatSubject_tab": "Group portraits--Pennsylvania--Pittsburgh.Women--Pennsylvania--Pittsburgh.Men--Pennsylvania--Pittsburgh.Children--Pennsylvania--Pittsburgh.Churches--Pennsylvania--Pittsburgh.Washington, Robert.",
	"AdmGUIDValue_tab": "090d499b-5fe9-4540-aaf6-112f3a21c95d",
	"AdmPublishWebNoPassword": "Yes",
	"MultiMedia_irn": 38802,
	"MulMultiMediaRef_key": 20453,
	"image_url": "https://cmoa-collection-images.s3.amazonaws.com/teenie/38802/sizes/32373-1680.jpg"
}