{
	"ecatalogue_key": 20783,
	"irn": 32712,
	"TitAccessionNo": "2001.35.20814",
	"CreDateCreated": "1967",
	"CreEarliestDate": "1967",
	"CreLatestDate": "1967",
	"PhyMediumComments": "black-and-white: Kodak safety film",
	"CatDescriptText": "",
	"TitMainTitle": "Three women wearing dark dresses and disc jockey Rev. Bill Powell standing behind podium, in Central Baptist Church with Anniversary banner in background",
	"CreCountry_tab": "United States",
	"CreState_tab": "",
	"CreDistrict_tab": "",
	"CreCity_tab": "",
	"CrePlaceQualifier_tab": "",
	"CatSubject_tab": "Men--Pennsylvania--Pittsburgh.Women--Pennsylvania--Pittsburgh.Central Baptist Church (Pittsburgh, Pa.)Churches--Pennsylvania--Pittsburgh.Stained glass--Pennsylvania--Pittsburgh.",
	"AdmGUIDValue_tab": "0473540b-f9fe-44ab-98a4-56d4bd9226c7",
	"AdmPublishWebNoPassword": "Yes",
	"MultiMedia_irn": 39067,
	"MulMultiMediaRef_key": 20791,
	"image_url": "https://cmoa-collection-images.s3.amazonaws.com/teenie/39067/sizes/32712-1680.jpg"
}