{
	"ecatalogue_key": 24973,
	"irn": 37347,
	"TitAccessionNo": "2001.35.25005",
	"CreDateCreated": "c. 1940-1955",
	"CreEarliestDate": "1940",
	"CreLatestDate": "1955",
	"PhyMediumComments": "black-and-white: Kodak safety film",
	"CatDescriptText": "",
	"TitMainTitle": "Portrait of woman wearing earrings, necklace, and light colored dress with pleated bodice and v neck, in Harris Studio, closer version",
	"CreCountry_tab": "United States",
	"CreState_tab": "",
	"CreDistrict_tab": "",
	"CreCity_tab": "",
	"CrePlaceQualifier_tab": "",
	"CatSubject_tab": "Women--Pennsylvania--Pittsburgh.Portraits--Pennsylvania--Pittsburgh.Studio portraits--Pennsylvania--Pittsburgh.Harris Studio (Pittsburgh, Pa.)Women--Portraits--Pennsylvania--Pittsburgh.",
	"AdmGUIDValue_tab": "07e9f173-6be1-4464-9a6c-c88ab66c598b",
	"AdmPublishWebNoPassword": "Yes",
	"MultiMedia_irn": 43579,
	"MulMultiMediaRef_key": 24981,
	"image_url": "https://cmoa-collection-images.s3.amazonaws.com/teenie/43579/sizes/37347-1680.jpg"
}