{
	"ecatalogue_key": 37244,
	"irn": 50343,
	"TitAccessionNo": "2001.35.37284",
	"CreDateCreated": "c. 1940-1955",
	"CreEarliestDate": "1940",
	"CreLatestDate": "1955",
	"PhyMediumComments": "black-and-white: unknown safety film",
	"CatDescriptText": "",
	"TitMainTitle": "Full length group portrait of three women, two wearing bathing suits, standing in sand, other men and women gathered in sand in background",
	"CreCountry_tab": "United States",
	"CreState_tab": "",
	"CreDistrict_tab": "",
	"CreCity_tab": "",
	"CrePlaceQualifier_tab": "",
	"CatSubject_tab": "Group portraits--Pennsylvania--Pittsburgh.Women--Pennsylvania--Pittsburgh.Bathing suits--Pennsylvania--Pittsburgh.",
	"AdmGUIDValue_tab": "57279f3b-23be-4099-b84f-07d7872b0309",
	"AdmPublishWebNoPassword": "Yes",
	"MultiMedia_irn": 57977,
	"MulMultiMediaRef_key": 37252,
	"image_url": "https://cmoa-collection-images.s3.amazonaws.com/teenie/57977/sizes/50343-1680.jpg"
}