{
	"ecatalogue_key": 41155,
	"irn": 54427,
	"TitAccessionNo": "2001.35.41197",
	"CreDateCreated": "c. 1945-1955",
	"CreEarliestDate": "1945",
	"CreLatestDate": "1955",
	"PhyMediumComments": "black-and-white: Kodak safety film",
	"CatDescriptText": "",
	"TitMainTitle": "Two women, including one wearing dark spaghetti strapped dress with dark lace overlay, three light colored buttons, and light colored belt and flower corsage on chest, and four men, posed standing in interior behind table with flowers in flower pots, light colored padded wall in background",
	"CreCountry_tab": "United States",
	"CreState_tab": "",
	"CreDistrict_tab": "",
	"CreCity_tab": "",
	"CrePlaceQualifier_tab": "",
	"CatSubject_tab": "Group portraits--Pennsylvania--Pittsburgh.Men--Pennsylvania--Pittsburgh.Interiors--Pennsylvania--Pittsburgh.Women--Pennsylvania--Pittsburgh.Tables--Pennsylvania--Pittsburgh.Flowers--Pennsylvania--Pittsburgh.",
	"AdmGUIDValue_tab": "54ce32ad-4381-4c7d-baee-c024f6cdf172",
	"AdmPublishWebNoPassword": "Yes",
	"MultiMedia_irn": 61837,
	"MulMultiMediaRef_key": 41163,
	"image_url": "https://cmoa-collection-images.s3.amazonaws.com/teenie/61837/sizes/54427-1680.jpg"
}