{
	"ecatalogue_key": 45188,
	"irn": 59118,
	"TitAccessionNo": "2001.35.45231",
	"CreDateCreated": "c. 1956",
	"CreEarliestDate": "1953",
	"CreLatestDate": "1959",
	"PhyMediumComments": "black-and-white: Kodak safety film",
	"CatDescriptText": "",
	"TitMainTitle": "Portrait of man wearing cook or chef's uniform with apron and cap, posed in restaurant kitchen with frying baskets in background",
	"CreCountry_tab": "United States",
	"CreState_tab": "",
	"CreDistrict_tab": "",
	"CreCity_tab": "",
	"CrePlaceQualifier_tab": "",
	"CatSubject_tab": "Portraits--Pennsylvania--Pittsburgh.Men--Pennsylvania--Pittsburgh.Cooks--Pennsylvania--Pittsburgh.Kitchens--Pennsylvania--Pittsburgh.Men--Portraits--Pennsylvania--Pittsburgh.",
	"AdmGUIDValue_tab": "15e0133f-4db4-4003-b3ec-5acfc78cd413",
	"AdmPublishWebNoPassword": "Yes",
	"MultiMedia_irn": 67362,
	"MulMultiMediaRef_key": 45196,
	"image_url": "https://cmoa-collection-images.s3.amazonaws.com/teenie/67362/sizes/59118-1680.jpg"
}