{
	"ecatalogue_key": 46198,
	"irn": 60192,
	"TitAccessionNo": "2001.35.46241",
	"CreDateCreated": "c. 1957",
	"CreEarliestDate": "1954",
	"CreLatestDate": "1960",
	"PhyMediumComments": "black-and-white: Kodak safety film",
	"CatDescriptText": "",
	"TitMainTitle": "Pittsburgh's Point, seen from south bank of Monongahela River",
	"CreCountry_tab": "United States",
	"CreState_tab": "",
	"CreDistrict_tab": "",
	"CreCity_tab": "",
	"CrePlaceQualifier_tab": "",
	"CatSubject_tab": "Point (Pittsburgh, Pa.)Monongahela River (W. Va. and Pa.).Locks and Dam No. 1.Allegheny River (Pa. and N.Y.)Downtown (Pittsburgh, Pa.)Bridges--Pennsylvania--Pittsburgh.Rivers--Pennsylvania--Pittsburgh.",
	"AdmGUIDValue_tab": "6526c72d-71a3-40bd-8a0d-195d233f319f",
	"AdmPublishWebNoPassword": "Yes",
	"MultiMedia_irn": 68653,
	"MulMultiMediaRef_key": 46206,
	"image_url": "https://cmoa-collection-images.s3.amazonaws.com/teenie/68653/sizes/60192-1680.jpg"
}