{
	"ecatalogue_key": 4627,
	"irn": 7527,
	"TitAccessionNo": "2001.35.4636",
	"CreDateCreated": "c. 1960-1975",
	"CreEarliestDate": "1960",
	"CreLatestDate": "1975",
	"PhyMediumComments": "black-and-white: Kodak safety film",
	"CatDescriptText": "",
	"TitMainTitle": "Children crossing street with adults holding placards protesting lack of crossing guard, including one sign reading \"Mr. Burrel did not keep his word\"",
	"CreCountry_tab": "United States",
	"CreState_tab": "Pennsylvania",
	"CreDistrict_tab": "Allegheny county",
	"CreCity_tab": "Pittsburgh",
	"CrePlaceQualifier_tab": "",
	"CatSubject_tab": "Signs--Pennsylvania--Pittsburgh.Picketing--Pennsylvania--Pittsburgh.Men--Pennsylvania--Pittsburgh.Women--Pennsylvania--Pittsburgh.Children--Pennsylvania--Pittsburgh.Streets--Pennsylvania--Pittsburgh.Schoolchildren--Pennsylvania--Pittsburgh.",
	"AdmGUIDValue_tab": "9d9bf400-34fb-49d1-bda4-6e998a654bbb",
	"AdmPublishWebNoPassword": "Yes",
	"MultiMedia_irn": 20131,
	"MulMultiMediaRef_key": 4630,
	"image_url": "https://cmoa-collection-images.s3.amazonaws.com/teenie/20131/sizes/7527-1680.jpg"
}