{
    "objectID": 21216,
    "irn": 21216,
    "ecatalogue_key": 11937,
    "TitAccessionNo": "2001.35.11967",
    "CreDateCreated": "1970",
    "CreEarliestDate": "1970",
    "CreLatestDate": "1970",
    "PhyMediumComments": "black-and-white: Kodak safety film",
    "CatDescriptText": "",
    "TitMainTitle": "Woman graduate wearing cap and gown, posing beside floral sofa",
    "CreCountry_tab": "United States",
    "CreState_tab": "",
    "CreDistrict_tab": "",
    "CreCity_tab": "",
    "CrePlaceQualifier_tab": "",
    "CatSubject_tab": "Women--Pennsylvania--Pittsburgh.",
    "AdmGUIDValue_tab": "b6a275f2-bb0e-4c05-8336-447978b1b03c",
    "AdmPublishWebNoPassword": "Yes",
    "MultiMedia_irn": 27861,
    "MulMultiMediaRef_key": 11945,
    "image_url": "https://cmoa-collection-images.s3.amazonaws.com/teenie/27861/sizes/21216-1680.jpg",
    "date_timestamp_earliest": 0.0,
    "date_timestamp_latest": 0.0,
    "decades": [
        "1970s"
    ],
    "people": [],
    "places": [
        {
            "type": "place",
            "score": 100,
            "long_name": "Pennsylvania",
            "short_name": "Pennsylvania"
        },
        {
            "type": "place",
            "score": 100,
            "long_name": "Pittsburgh",
            "short_name": "Pittsburgh"
        }
    ],
    "bibliography": {},
    "people_count": 1,
    "google_text_in_image": "",
    "subjects": [
        "Women"
    ],
    "keywords": [
        {
            "keyword": "mortarboard",
            "score": 0.6172364666666666
        },
        {
            "keyword": "graduation",
            "score": 0.427763402454427
        },
        {
            "keyword": "Women",
            "score": 0.3333333333333333
        },
        {
            "keyword": "cap",
            "score": 0.3333333333333333
        },
        {
            "keyword": "academic dress",
            "score": 0.31244673333333334
        },
        {
            "keyword": "standing",
            "score": 0.2981091560119629
        },
        {
            "keyword": "black and white",
            "score": 0.28646136666666666
        },
        {
            "keyword": "headdress",
            "score": 0.28642773946126304
        },
        {
            "keyword": "portrait",
            "score": 0.28004874662272133
        },
        {
            "keyword": "photography",
            "score": 0.2622659333333333
        },
        {
            "keyword": "academician",
            "score": 0.25264400000000004
        },
        {
            "keyword": "clothing",
            "score": 0.22970822652181
        },
        {
            "keyword": "phd",
            "score": 0.22926751666666667
        },
        {
            "keyword": "monochrome photography",
            "score": 0.21270722
        },
        {
            "keyword": "monochrome",
            "score": 0.20754433333333333
        }
    ]
}