{
    "objectID": 40852,
    "irn": 40852,
    "ecatalogue_key": 28282,
    "TitAccessionNo": "2001.35.28314",
    "CreDateCreated": "c. 1943",
    "CreEarliestDate": "1938",
    "CreLatestDate": "1948",
    "PhyMediumComments": "black-and-white: Agfa safety film",
    "CatDescriptText": "",
    "TitMainTitle": "Group portrait of four men, and seven women, one wearing light colored dress with swirl patterned panels, seated at table in domestic interior with fireplace and built in china cabinet in background",
    "CreCountry_tab": "United States",
    "CreState_tab": "",
    "CreDistrict_tab": "",
    "CreCity_tab": "",
    "CrePlaceQualifier_tab": "",
    "CatSubject_tab": "Men--Pennsylvania--Pittsburgh.Women--Pennsylvania--Pittsburgh.Group portraits--Pennsylvania--Pittsburgh.Dining rooms--Pennsylvania--Pittsburgh.",
    "AdmGUIDValue_tab": "1d08d184-d3cd-4a6a-a764-73c29c1504cc",
    "AdmPublishWebNoPassword": "Yes",
    "MultiMedia_irn": 47164,
    "MulMultiMediaRef_key": 28290,
    "image_url": "https://cmoa-collection-images.s3.amazonaws.com/teenie/47164/sizes/40852-1680.jpg",
    "date_timestamp_earliest": -1009843200.0,
    "date_timestamp_latest": -694310400.0,
    "decades": [],
    "people": [],
    "places": [
        {
            "type": "place",
            "score": 100,
            "long_name": "china",
            "short_name": "china"
        },
        {
            "type": "place",
            "score": 100,
            "long_name": "Pennsylvania",
            "short_name": "Pennsylvania"
        },
        {
            "type": "place",
            "score": 100,
            "long_name": "Pittsburgh",
            "short_name": "Pittsburgh"
        }
    ],
    "bibliography": {},
    "people_count": 11,
    "google_text_in_image": "",
    "subjects": [
        "Dining rooms",
        "Men",
        "Women",
        "Portraits, Group"
    ],
    "keywords": [
        {
            "keyword": "room",
            "score": 0.4024290594230144
        },
        {
            "keyword": "home",
            "score": 0.340278442141927
        },
        {
            "keyword": "Dining rooms",
            "score": 0.3333333333333333
        },
        {
            "keyword": "Men",
            "score": 0.3333333333333333
        },
        {
            "keyword": "Women",
            "score": 0.3333333333333333
        },
        {
            "keyword": "Group portraits",
            "score": 0.3333333333333333
        },
        {
            "keyword": "table",
            "score": 0.311879880583903
        },
        {
            "keyword": "furniture",
            "score": 0.307370373257243
        },
        {
            "keyword": "house",
            "score": 0.2992215887308757
        },
        {
            "keyword": "black and white",
            "score": 0.28518394666666663
        },
        {
            "keyword": "snapshot",
            "score": 0.27255816666666666
        },
        {
            "keyword": "photography",
            "score": 0.26235953333333334
        },
        {
            "keyword": "vintage clothing",
            "score": 0.2612586
        },
        {
            "keyword": "family",
            "score": 0.238825242014567
        },
        {
            "keyword": "monochrome photography",
            "score": 0.22882465666666665
        },
        {
            "keyword": "window",
            "score": 0.20507948324890135
        }
    ]
}