{
    "objectID": 41336,
    "irn": 41336,
    "ecatalogue_key": 28677,
    "TitAccessionNo": "2001.35.28709",
    "CreDateCreated": "c. 1944",
    "CreEarliestDate": "1939",
    "CreLatestDate": "1949",
    "PhyMediumComments": "black-and-white: Agfa safety film",
    "CatDescriptText": "",
    "TitMainTitle": "Portrait of man wearing U. S. Army uniform with light colored tie tucked into shirt, Sergeant patch on sleeve, and Army Air Force patch on shoulder, and dark cap, seated in front of light colored circular background, in Harris Studio",
    "CreCountry_tab": "United States",
    "CreState_tab": "",
    "CreDistrict_tab": "",
    "CreCity_tab": "",
    "CrePlaceQualifier_tab": "",
    "CatSubject_tab": "Men--Pennsylvania--Pittsburgh.Portraits--Pennsylvania--Pittsburgh.Military uniforms--Pennsylvania--Pittsburgh.Studio portraits--Pennsylvania--Pittsburgh.Harris Studio (Pittsburgh, Pa.)Men--Portraits--Pennsylvania--Pittsburgh.Soldiers--Pennsylvania--Pittsburgh--Portraits.",
    "AdmGUIDValue_tab": "ea4ac6c5-d3e3-4680-84c2-47fca0a91410",
    "AdmPublishWebNoPassword": "Yes",
    "MultiMedia_irn": 47887,
    "MulMultiMediaRef_key": 28685,
    "image_url": "https://cmoa-collection-images.s3.amazonaws.com/teenie/47887/sizes/41336-1680.jpg",
    "date_timestamp_earliest": -978307200.0,
    "date_timestamp_latest": -662688000.0,
    "decades": [],
    "people": [],
    "places": [
        {
            "type": "place",
            "score": 100,
            "long_name": "Pennsylvania",
            "short_name": "Pennsylvania"
        },
        {
            "type": "place",
            "score": 100,
            "long_name": "Pittsburgh",
            "short_name": "Pittsburgh"
        }
    ],
    "bibliography": {},
    "people_count": 1,
    "google_text_in_image": "",
    "subjects": [
        "Men",
        "Portraits",
        "Soldiers",
        "Military uniforms"
    ],
    "keywords": [
        {
            "keyword": "man",
            "score": 0.393229085349528
        },
        {
            "keyword": "person",
            "score": 0.3769602133199057
        },
        {
            "keyword": "portrait",
            "score": 0.35140596467040996
        },
        {
            "keyword": "male",
            "score": 0.3338310784016927
        },
        {
            "keyword": "Portraits",
            "score": 0.3333333333333333
        },
        {
            "keyword": "Men",
            "score": 0.3333333333333333
        },
        {
            "keyword": "Army Air Force",
            "score": 0.3333333333333333
        },
        {
            "keyword": "Military uniforms",
            "score": 0.3333333333333333
        },
        {
            "keyword": ")Men",
            "score": 0.3333333333333333
        },
        {
            "keyword": "Harris Studio",
            "score": 0.3333333333333333
        },
        {
            "keyword": "Studio portraits",
            "score": 0.3333333333333333
        },
        {
            "keyword": "Soldiers",
            "score": 0.3333333333333333
        },
        {
            "keyword": "Harris Studio ",
            "score": 0.3333333333333333
        },
        {
            "keyword": "U. S. Army",
            "score": 0.3333333333333333
        },
        {
            "keyword": "black and white",
            "score": 0.3069512833333333
        },
        {
            "keyword": "sitting",
            "score": 0.28757266666666664
        },
        {
            "keyword": "standing",
            "score": 0.28669262
        },
        {
            "keyword": "monochrome photography",
            "score": 0.28156783333333335
        },
        {
            "keyword": "photography",
            "score": 0.28065425
        },
        {
            "keyword": "snapshot",
            "score": 0.27255816666666666
        },
        {
            "keyword": "human",
            "score": 0.2646507411671956
        },
        {
            "keyword": "gentleman",
            "score": 0.2619995666666667
        },
        {
            "keyword": "monochrome",
            "score": 0.23584566666666665
        },
        {
            "keyword": "smile",
            "score": 0.2293438696725464
        },
        {
            "keyword": "hat",
            "score": 0.22812583923339835
        },
        {
            "keyword": "cool",
            "score": 0.22234594666666666
        },
        {
            "keyword": "portrait photography",
            "score": 0.21368050000000002
        }
    ]
}