{
    "objectID": 65465,
    "irn": 65465,
    "ecatalogue_key": 51319,
    "TitAccessionNo": "2001.35.51362",
    "CreDateCreated": "c. 1955",
    "CreEarliestDate": "1952",
    "CreLatestDate": "1958",
    "PhyMediumComments": "black-and-white: Kodak safety film",
    "CatDescriptText": "",
    "TitMainTitle": "Group portrait of groom standing, wearing heart patterned necktie and light colored carnation, with smiling bride wearing earrings, necklace, light colored long sleeved v-neck wedding dress with corsage on left shoulder, posed on chair in domestic interior with floral wallpaper, window, radiator, and china cabinet, possibly for Lewis wedding",
    "CreCountry_tab": "United States",
    "CreState_tab": "",
    "CreDistrict_tab": "",
    "CreCity_tab": "",
    "CrePlaceQualifier_tab": "",
    "CatSubject_tab": "Group portraits--Pennsylvania--Pittsburgh.Interiors--Pennsylvania--Pittsburgh.Flowers--Pennsylvania--Pittsburgh.Chairs--Pennsylvania--Pittsburgh.Wallpaper--Pennsylvania--Pittsburgh.Men--Pennsylvania--Pittsburgh.Bridegrooms--Pennsylvania--Pittsburgh.Furniture--Pennsylvania--Pittsburgh.Women--Pennsylvania--Pittsburgh.Brides--Pennsylvania--Pittsburgh.Windows--Pennsylvania--Pittsburgh.Radiators--Pennsylvania--Pittsburgh.",
    "AdmGUIDValue_tab": "75fdf0c1-0f5c-41fa-9509-780b570efcb5",
    "AdmPublishWebNoPassword": "Yes",
    "MultiMedia_irn": 75106,
    "MulMultiMediaRef_key": 51327,
    "image_url": "https://cmoa-collection-images.s3.amazonaws.com/teenie/75106/sizes/65465-1680.jpg",
    "date_timestamp_earliest": -568080000.0,
    "date_timestamp_latest": -378691200.0,
    "decades": [
        "1950s"
    ],
    "people": [
        "Lewis"
    ],
    "places": [
        {
            "type": "place",
            "score": 100,
            "long_name": "Pennsylvania",
            "short_name": "Pennsylvania"
        },
        {
            "type": "place",
            "score": 100,
            "long_name": "Pittsburgh",
            "short_name": "Pittsburgh"
        }
    ],
    "bibliography": {},
    "people_count": 2,
    "google_text_in_image": "",
    "subjects": [
        "Radiators",
        "Interiors",
        "Brides",
        "Portraits, Group",
        "Furniture",
        "Men",
        "Windows",
        "Lewis",
        "Interior architecture",
        "Wallpaper",
        "Women",
        "Flowers",
        "Chairs",
        "Bridegrooms"
    ],
    "keywords": [
        {
            "keyword": "groom",
            "score": 0.5733644885721844
        },
        {
            "keyword": "man",
            "score": 0.44796788815104166
        },
        {
            "keyword": "family",
            "score": 0.3526055326171873
        },
        {
            "keyword": "suit",
            "score": 0.34383723456115733
        },
        {
            "keyword": "smile",
            "score": 0.340662680037435
        },
        {
            "keyword": "Radiators",
            "score": 0.3333333333333333
        },
        {
            "keyword": "Interiors",
            "score": 0.3333333333333333
        },
        {
            "keyword": "Brides",
            "score": 0.3333333333333333
        },
        {
            "keyword": "Furniture",
            "score": 0.3333333333333333
        },
        {
            "keyword": "Group portraits",
            "score": 0.3333333333333333
        },
        {
            "keyword": "Men",
            "score": 0.3333333333333333
        },
        {
            "keyword": "Windows",
            "score": 0.3333333333333333
        },
        {
            "keyword": "Lewis",
            "score": 0.3333333333333333
        },
        {
            "keyword": "Wallpaper",
            "score": 0.3333333333333333
        },
        {
            "keyword": "Women",
            "score": 0.3333333333333333
        },
        {
            "keyword": "Flowers",
            "score": 0.3333333333333333
        },
        {
            "keyword": "Chairs",
            "score": 0.3333333333333333
        },
        {
            "keyword": "Bridegrooms",
            "score": 0.3333333333333333
        },
        {
            "keyword": "standing",
            "score": 0.31781523272399903
        },
        {
            "keyword": "facial expression",
            "score": 0.31186831
        },
        {
            "keyword": "formal wear",
            "score": 0.30615526666666665
        },
        {
            "keyword": "dress",
            "score": 0.305932379379069
        },
        {
            "keyword": "fun",
            "score": 0.297948192617798
        },
        {
            "keyword": "black and white",
            "score": 0.29741315
        },
        {
            "keyword": "sitting",
            "score": 0.2908301204071044
        },
        {
            "keyword": "beauty",
            "score": 0.2856725666666667
        },
        {
            "keyword": "photography",
            "score": 0.2804459133333333
        },
        {
            "keyword": "snapshot",
            "score": 0.27255816666666666
        },
        {
            "keyword": "vintage clothing",
            "score": 0.26807580000000003
        },
        {
            "keyword": "monochrome photography",
            "score": 0.26532499
        },
        {
            "keyword": "gentleman",
            "score": 0.26500053333333334
        },
        {
            "keyword": "wedding",
            "score": 0.2595887333333333
        },
        {
            "keyword": "event",
            "score": 0.25071619
        },
        {
            "keyword": "bride",
            "score": 0.2503054333333333
        },
        {
            "keyword": "ceremony",
            "score": 0.23892482
        }
    ]
}