{
    "objectID": 71918,
    "irn": 71918,
    "ecatalogue_key": 56723,
    "TitAccessionNo": "2001.35.56766",
    "CreDateCreated": "c. 1962",
    "CreEarliestDate": "1959",
    "CreLatestDate": "1965",
    "PhyMediumComments": "black-and-white: Kodak safety film",
    "CatDescriptText": "",
    "TitMainTitle": "Young men seated, including one in center wearing light colored shirt, diagonally striped necktie, and striped jacket, raising left hand to mouth, dining at round table with light colored tablecloth in interior with chandeliers and curtains, possibly in Webster Hall for Kay Boys Club event",
    "CreCountry_tab": "United States",
    "CreState_tab": "",
    "CreDistrict_tab": "",
    "CreCity_tab": "",
    "CrePlaceQualifier_tab": "",
    "CatSubject_tab": "Kay Boys' Club (Pittsburgh, Pa.)Men--Pennsylvania--Pittsburgh.Interiors--Pennsylvania--Pittsburgh.Curtains--Pennsylvania--Pittsburgh.Webster Hall (Pittsburgh, Pa.)Boys--Pennsylvania--Pittsburgh.Young adults--Pennsylvania--Pittsburgh.Tables--Pennsylvania--Pittsburgh.Dinners and dining--Pennsylvania--Pittsburgh.Chandeliers--Pennsylvania--Pittsburgh.",
    "AdmGUIDValue_tab": "df24cfa1-45b4-4ad6-9942-7b4c96254109",
    "AdmPublishWebNoPassword": "Yes",
    "MultiMedia_irn": 89679,
    "MulMultiMediaRef_key": 56732,
    "image_url": "https://cmoa-collection-images.s3.amazonaws.com/teenie/89679/sizes/71918-1680.jpg",
    "date_timestamp_earliest": -347155200.0,
    "date_timestamp_latest": -157766400.0,
    "decades": [],
    "people": [],
    "places": [
        {
            "type": "place",
            "score": 100,
            "long_name": "Webster Hall",
            "short_name": "Webster Hall"
        },
        {
            "type": "place",
            "score": 100,
            "long_name": "Pennsylvania",
            "short_name": "Pennsylvania"
        },
        {
            "type": "place",
            "score": 100,
            "long_name": "Pittsburgh",
            "short_name": "Pittsburgh"
        }
    ],
    "bibliography": {},
    "people_count": 23,
    "google_text_in_image": "",
    "subjects": [
        "Dinners and dining",
        "Interiors",
        "Young adults",
        "Chandeliers",
        "Draperies",
        "Interior architecture",
        "Tables"
    ],
    "keywords": [
        {
            "keyword": "Dinners and dining",
            "score": 0.3333333333333333
        },
        {
            "keyword": "Kay Boys' Club ",
            "score": 0.3333333333333333
        },
        {
            "keyword": "Interiors",
            "score": 0.3333333333333333
        },
        {
            "keyword": "Curtains",
            "score": 0.3333333333333333
        },
        {
            "keyword": "Young adults",
            "score": 0.3333333333333333
        },
        {
            "keyword": "Kay Boys Club",
            "score": 0.3333333333333333
        },
        {
            "keyword": "Chandeliers",
            "score": 0.3333333333333333
        },
        {
            "keyword": "Webster Hall",
            "score": 0.3333333333333333
        },
        {
            "keyword": "Webster Hall ",
            "score": 0.3333333333333333
        },
        {
            "keyword": ")Boys",
            "score": 0.3333333333333333
        },
        {
            "keyword": ")Men",
            "score": 0.3333333333333333
        },
        {
            "keyword": "Tables",
            "score": 0.3333333333333333
        },
        {
            "keyword": "function hall",
            "score": 0.28687263333333335
        },
        {
            "keyword": "black and white",
            "score": 0.2862457666666667
        },
        {
            "keyword": "event",
            "score": 0.28290015333333335
        },
        {
            "keyword": "ceremony",
            "score": 0.27754628666666664
        },
        {
            "keyword": "fun",
            "score": 0.27316774262146
        },
        {
            "keyword": "photography",
            "score": 0.27023056666666667
        },
        {
            "keyword": "banquet",
            "score": 0.2676136666666667
        },
        {
            "keyword": "monochrome photography",
            "score": 0.23989020000000003
        },
        {
            "keyword": "party",
            "score": 0.23902153333333334
        },
        {
            "keyword": "restaurant",
            "score": 0.23401731333333334
        },
        {
            "keyword": "crowd",
            "score": 0.22503986666666667
        },
        {
            "keyword": "rehearsal dinner",
            "score": 0.20577178333333335
        }
    ]
}